i3ipc/__init__.py
i3ipc/__version__.py
i3ipc/con.py
i3ipc/connection.py
i3ipc/events.py
i3ipc/model.py
i3ipc/replies.py
i3ipc/_private/__init__.py
i3ipc/_private/pubsub.py
i3ipc/_private/types.py
i3ipc/aio/__init__.py
i3ipc/aio/connection.py
i3ipc-2.1.1.dist-info/LICENSE
i3ipc-2.1.1.dist-info/METADATA
i3ipc-2.1.1.dist-info/WHEEL
i3ipc-2.1.1.dist-info/top_level.txt
i3ipc-2.1.1.dist-info/RECORD
