Metadata-Version: 2.1
Name: i3ipc
Version: 2.1.1
Summary: An improved Python library to control i3wm and sway
Home-page: https://github.com/altdesktop/i3ipc-python
Author: Tony Crisci
Author-email: tony@dubstepdish.com
License: BSD
Keywords: i3 i3wm extensions add-ons
Platform: UNKNOWN
Classifier: Development Status :: 4 - Beta
Classifier: Intended Audience :: Developers
Classifier: License :: OSI Approved :: BSD License
Classifier: Programming Language :: Python :: 3.4
Classifier: Programming Language :: Python :: 3.5
Classifier: Programming Language :: Python :: 3.6
Classifier: Programming Language :: Python :: 3.7
Requires-Python: >=3.4.0
Requires-Dist: enum-compat
Requires-Dist: python-xlib
